README.txt
setup.cfg
setup.py
collective/__init__.py
collective.FolderContentsPortletManager.egg-info/PKG-INFO
collective.FolderContentsPortletManager.egg-info/SOURCES.txt
collective.FolderContentsPortletManager.egg-info/dependency_links.txt
collective.FolderContentsPortletManager.egg-info/entry_points.txt
collective.FolderContentsPortletManager.egg-info/namespace_packages.txt
collective.FolderContentsPortletManager.egg-info/not-zip-safe
collective.FolderContentsPortletManager.egg-info/paster_plugins.txt
collective.FolderContentsPortletManager.egg-info/requires.txt
collective.FolderContentsPortletManager.egg-info/top_level.txt
collective/FolderContentsPortletManager/__init__.py
collective/FolderContentsPortletManager/configure.zcml
collective/FolderContentsPortletManager/tests.py
collective/FolderContentsPortletManager/browser/__init__.py
collective/FolderContentsPortletManager/browser/configure.zcml
collective/FolderContentsPortletManager/browser/folder_contents.pt
collective/FolderContentsPortletManager/browser/foldercontents.pt
collective/FolderContentsPortletManager/browser/foldercontents.py
collective/FolderContentsPortletManager/browser/interfaces.py
collective/FolderContentsPortletManager/browser/managefoldercontents.pt
collective/FolderContentsPortletManager/browser/table.pt
collective/FolderContentsPortletManager/profiles/default/browserlayer.xml
collective/FolderContentsPortletManager/profiles/default/metadata.xml
collective/FolderContentsPortletManager/profiles/default/portlets.xml
docs/HISTORY.txt
docs/INSTALL.txt
docs/LICENSE.GPL
docs/LICENSE.txt