Metadata-Version: 1.0
Name: collective.FolderContentsPortletManager
Version: 0.2
Summary: Portlet manager for the folder_contents (contents tab). Usefull to add a mass uploader portlet for example
Home-page: http://svn.plone.org/svn/collective/
Author: David Jonas
Author-email: david@intk.com
License: GPL
Keywords: product portlet folder contents tab
Platform: UNKNOWN
Classifier: Framework :: Plone
Classifier: Programming Language :: Python
